freesixty/__init__.py
freesixty/freesixty.py
freesixty-0.1.32.dist-info/METADATA
freesixty-0.1.32.dist-info/RECORD
freesixty-0.1.32.dist-info/WHEEL
freesixty-0.1.32.dist-info/top_level.txt
