Metadata-Version: 2.1
Name: freesixty
Version: 0.1.32
Summary: Simple Google Analytics API data extraction.
Home-page: https://github.com/datatart/freesixty
Author: Rok Mihevc
Author-email: me@rok.dev
License: MIT
Platform: UNKNOWN
Classifier: License :: OSI Approved :: MIT License
Classifier: Programming Language :: Python
Classifier: Programming Language :: Python :: 3
Classifier: Programming Language :: Python :: 3.6
Classifier: Programming Language :: Python :: Implementation :: CPython
Classifier: Programming Language :: Python :: Implementation :: PyPy
Requires-Python: >=3.6.0
Requires-Dist: boto3
Requires-Dist: google-api-python-client
Requires-Dist: oauth2client
Requires-Dist: httplib2
